tabsdata_snowflake-1.5.0.data/purelib/tabsdata_snowflake/__init__.py
tabsdata_snowflake-1.5.0.data/purelib/tabsdata_snowflake/_connector.py
tabsdata_snowflake-1.5.0.data/purelib/tabsdata_snowflake/assets/manifest/BANNER
tabsdata_snowflake-1.5.0.data/purelib/tabsdata_snowflake/assets/manifest/LICENSE
tabsdata_snowflake-1.5.0.data/purelib/tabsdata_snowflake/assets/manifest/README-PyPi.md
tabsdata_snowflake-1.5.0.data/purelib/tabsdata_snowflake/assets/manifest/RELEASE-NOTES
tabsdata_snowflake-1.5.0.data/purelib/tabsdata_snowflake/assets/manifest/SOURCETRACK.yaml
tabsdata_snowflake-1.5.0.data/purelib/tabsdata_snowflake/assets/manifest/THIRD-PARTY
tabsdata_snowflake-1.5.0.data/purelib/tabsdata_snowflake/assets/manifest/VERSION
tabsdata_snowflake-1.5.0.dist-info/licenses/tabsdata_snowflake/assets/manifest/LICENSE
tabsdata_snowflake-1.5.0.dist-info/METADATA
tabsdata_snowflake-1.5.0.dist-info/WHEEL
tabsdata_snowflake-1.5.0.dist-info/top_level.txt
tabsdata_snowflake-1.5.0.dist-info/RECORD
